sotabenchapi/__init__.py
sotabenchapi/__main__.py
sotabenchapi/check.py
sotabenchapi/client.py
sotabenchapi/config.py
sotabenchapi/consts.py
sotabenchapi/errors.py
sotabenchapi/http.py
sotabenchapi/version.py
sotabenchapi/commands/__init__.py
sotabenchapi/commands/build.py
sotabenchapi/commands/check.py
sotabenchapi/commands/cli.py
sotabenchapi/commands/repo.py
sotabenchapi/commands/utils.py
sotabenchapi/core/__init__.py
sotabenchapi/core/inputs.py
sotabenchapi/core/results.py
sotabenchapi/tests/__init__.py
sotabenchapi/tests/test_client.py
sotabenchapi-0.0.16.dist-info/LICENSE
sotabenchapi-0.0.16.dist-info/METADATA
sotabenchapi-0.0.16.dist-info/WHEEL
sotabenchapi-0.0.16.dist-info/entry_points.txt
sotabenchapi-0.0.16.dist-info/top_level.txt
sotabenchapi-0.0.16.dist-info/RECORD
