Metadata-Version: 2.1
Name: sotabenchapi
Version: 0.0.16
Summary: Easily benchmark Machine Learning models on selected tasks and datasets.
Home-page: https://sotabench.com
Author: Robert Stojnic
Author-email: hello@sotabench.com
Maintainer: Robert Stojnic
Maintainer-email: hello@sotabench.com
License: Apache-2.0
Platform: Windows
Platform: POSIX
Platform: MacOSX
Requires-Dist: click (==7.0)
Requires-Dist: requests (==2.22.0)
Requires-Dist: tabulate (==0.8.3)
